azure/maps/render/__init__.py
azure/maps/render/_client.py
azure/maps/render/_configuration.py
azure/maps/render/_enums.py
azure/maps/render/_patch.py
azure/maps/render/_serialization.py
azure/maps/render/_version.py
azure/maps/render/py.typed
azure/maps/render/aio/__init__.py
azure/maps/render/aio/_client.py
azure/maps/render/aio/_configuration.py
azure/maps/render/aio/_patch.py
azure/maps/render/aio/operations/__init__.py
azure/maps/render/aio/operations/_operations.py
azure/maps/render/aio/operations/_patch.py
azure/maps/render/operations/__init__.py
azure/maps/render/operations/_operations.py
azure/maps/render/operations/_patch.py
azure_maps_render-2.0.0b2.dist-info/METADATA
azure_maps_render-2.0.0b2.dist-info/WHEEL
azure_maps_render-2.0.0b2.dist-info/top_level.txt
azure_maps_render-2.0.0b2.dist-info/RECORD
