Metadata-Version: 2.1
Name: azure-maps-render
Version: 2.0.0b2
Summary: Microsoft Azure Maps Render Client Library for Python
Home-page: https://github.com/Azure/azure-sdk-for-python/tree/main/sdk/maps/azure-maps-render
Author: Microsoft Corporation
Author-email: azpysdkhelp@microsoft.com
License: MIT License
Keywords: azure,azure sdk
Classifier: Development Status :: 4 - Beta
Classifier: Programming Language :: Python
Classifier: Programming Language :: Python :: 3
Classifier: Programming Language :: Python :: 3 :: Only
Classifier: Programming Language :: Python :: 3.8
Classifier: Programming Language :: Python :: 3.9
Classifier: Programming Language :: Python :: 3.10
Classifier: Programming Language :: Python :: 3.11
Classifier: Programming Language :: Python :: 3.12
Classifier: License :: OSI Approved :: MIT License
Requires-Python: >=3.8
Requires-Dist: msrest >=0.6.21
Requires-Dist: azure-common ~=1.1
Requires-Dist: azure-mgmt-core <2.0.0,>=1.3.0
